pytest_html_profiling/__init__.py
pytest_html_profiling/extras.py
pytest_html_profiling/hooks.py
pytest_html_profiling/plugin.py
pytest_html_profiling/profiling_plugin.py
pytest_html_profiling/resources/main.js
pytest_html_profiling/resources/readable.css
pytest_html_profiling/resources/style.css
pytest_html_profiling-1.0.0.dist-info/LICENSE
pytest_html_profiling-1.0.0.dist-info/METADATA
pytest_html_profiling-1.0.0.dist-info/WHEEL
pytest_html_profiling-1.0.0.dist-info/entry_points.txt
pytest_html_profiling-1.0.0.dist-info/top_level.txt
pytest_html_profiling-1.0.0.dist-info/RECORD
