Metadata-Version: 2.1
Name: pytest-html-profiling
Version: 1.0.0
Summary: Pytest plugin for generating HTML reports with per-test profiling and optionally call graph visualizations. Based on pytest-html by Dave Hunt.
Home-page: https://github.com/hyperbrowser/pytest-html-profiling
Author: Radmila Kompova and Sveinung Gundersen
Author-email: radmilko@ifi.uio.no, sveinugu@gmail.com
License: Mozilla Public License 2.0 (MPL 2.0)
Keywords: py.test pytest html report
Platform: UNKNOWN
Classifier: Development Status :: 5 - Production/Stable
Classifier: Framework :: Pytest
Classifier: Intended Audience :: Developers
Classifier: License :: OSI Approved :: Mozilla Public License 2.0 (MPL 2.0)
Classifier: Operating System :: POSIX
Classifier: Operating System :: Microsoft :: Windows
Classifier: Operating System :: MacOS :: MacOS X
Classifier: Topic :: Software Development :: Quality Assurance
Classifier: Topic :: Software Development :: Testing
Classifier: Topic :: Utilities
Classifier: Programming Language :: Python :: 2.7
Requires-Dist: pytest (>=3.0)
Requires-Dist: pytest-metadata
Requires-Dist: pygraphviz
Requires-Dist: gprof2dot
